<?xml version="1.0" encoding="UTF-8"?>
<!DOCTYPE plist PUBLIC "-//Apple//DTD PLIST 1.0//EN" "http://www.apple.com/DTDs/PropertyList-1.0.dtd"/>

<plist version="1.0">
    <dict>
        <key>ROOT</key>
        <array>
            <dict>
                <key>id</key>
                <string>4276</string>
                <key>className</key>
                <string>PTModelObjectAssetPath</string>
                <key>Name</key>
                <dict>
                    <key>value</key>
                    <string>Path</string>
                </dict>
                <key>Position</key>
                <dict>
                    <key>value</key>
                    <string>{206.734,523.434}</string>
                    <key>animationsX</key>
                    <array/>
                    <key>animationsY</key>
                    <array/>
                </dict>
                <key>Rotation</key>
                <dict>
                    <key>animations</key>
                    <array/>
                </dict>
                <key>Scale</key>
                <dict>
                    <key>value</key>
                    <string>{1.000,1.000}</string>
                    <key>animationsX</key>
                    <array/>
                    <key>animationsY</key>
                    <array/>
                </dict>
                <key>Hidden</key>
                <dict>
                    <key>visible</key>
                    <string>0</string>
                </dict>
                <key>Locked</key>
                <dict>
                    <key>visible</key>
                    <string>0</string>
                </dict>
                <key>Opacity</key>
                <dict>
                    <key>animations</key>
                    <array/>
                </dict>
                <key>Play Mode</key>
                <dict>
                    <key>selectedStringValue</key>
                    <string>kPlayModeSingle</string>
                </dict>
                <key>Affected Asset</key>
                <dict>
                    <key>selectedStringValue</key>
                    <string>kAll</string>
                </dict>
                <key>zDepth</key>
                <string>502</string>
                <key>points</key>
                <array>
                    <string>{17.594,-35.189}</string>
                    <string>{48.385,-74.777}</string>
                    <string>{79.175,-101.168}</string>
                    <string>{123.161,-131.958}</string>
                    <string>{369.483,-79.175}</string>
                    <string>{681.784,-0.000}</string>
                    <string>{809.343,-74.777}</string>
                    <string>{835.735,17.594}</string>
                    <string>{193.539,-109.965}</string>
                    <string>{144.497,-119.707}</string>
                    <string>{101.168,-118.763}</string>
                    <string>{39.587,-118.763}</string>
                    <string>{-26.392,-118.763}</string>
                </array>
            </dict>
            <dict>
                <key>id</key>
                <string>4580</string>
                <key>className</key>
                <string>PTModelObjectAssetPath</string>
                <key>Name</key>
                <dict>
                    <key>value</key>
                    <string>Path</string>
                </dict>
                <key>Position</key>
                <dict>
                    <key>value</key>
                    <string>{241.923,536.630}</string>
                    <key>animationsX</key>
                    <array/>
                    <key>animationsY</key>
                    <array/>
                </dict>
                <key>Rotation</key>
                <dict>
                    <key>animations</key>
                    <array/>
                </dict>
                <key>Scale</key>
                <dict>
                    <key>value</key>
                    <string>{1.000,1.000}</string>
                    <key>animationsX</key>
                    <array/>
                    <key>animationsY</key>
                    <array/>
                </dict>
                <key>Hidden</key>
                <dict>
                    <key>visible</key>
                    <string>0</string>
                </dict>
                <key>Locked</key>
                <dict>
                    <key>visible</key>
                    <string>0</string>
                </dict>
                <key>Speed</key>
                <dict>
                    <key>value</key>
                    <string>20.000000</string>
                </dict>
                <key>Play Mode</key>
                <dict>
                    <key>selectedStringValue</key>
                    <string>kPlayModeLoop</string>
                </dict>
                <key>Affected Asset</key>
                <dict>
                    <key>selectedStringValue</key>
                    <string>kAll</string>
                </dict>
                <key>zDepth</key>
                <string>504</string>
                <key>points</key>
                <array>
                    <string>{4.399,-74.776}</string>
                    <string>{-8.797,-136.357}</string>
                    <string>{409.070,8.797}</string>
                    <string>{677.385,-153.951}</string>
                    <string>{1033.672,-35.189}</string>
                    <string>{659.791,-158.350}</string>
                    <string>{444.259,-17.594}</string>
                    <string>{109.965,-118.762}</string>
                    <string>{65.979,-123.161}</string>
                    <string>{4.399,-123.161}</string>
                    <string>{-70.378,-109.965}</string>
                </array>
            </dict>
            <dict>
                <key>id</key>
                <string>5038</string>
                <key>className</key>
                <string>PTModelObjectAssetPath</string>
                <key>Name</key>
                <dict>
                    <key>value</key>
                    <string>Path</string>
                </dict>
                <key>Position</key>
                <dict>
                    <key>value</key>
                    <string>{147.150,623.037}</string>
                    <key>animationsX</key>
                    <array/>
                    <key>animationsY</key>
                    <array/>
                </dict>
                <key>Rotation</key>
                <dict>
                    <key>animations</key>
                    <array/>
                </dict>
                <key>Scale</key>
                <dict>
                    <key>value</key>
                    <string>{1.000,1.000}</string>
                    <key>animationsX</key>
                    <array/>
                    <key>animationsY</key>
                    <array/>
                </dict>
                <key>Hidden</key>
                <dict>
                    <key>visible</key>
                    <string>0</string>
                </dict>
                <key>Locked</key>
                <dict>
                    <key>visible</key>
                    <string>0</string>
                </dict>
                <key>Opacity</key>
                <dict>
                    <key>animations</key>
                    <array/>
                </dict>
                <key>Play Mode</key>
                <dict>
                    <key>selectedStringValue</key>
                    <string>kPlayModeSingle</string>
                </dict>
                <key>Affected Asset</key>
                <dict>
                    <key>selectedStringValue</key>
                    <string>kAll</string>
                </dict>
                <key>zDepth</key>
                <string>501</string>
                <key>points</key>
                <array>
                    <string>{-6.262,-84.533}</string>
                    <string>{40.701,-144.019}</string>
                    <string>{40.701,-219.159}</string>
                    <string>{50.093,-140.888}</string>
                    <string>{40.701,-87.664}</string>
                    <string>{31.308,-15.654}</string>
                </array>
            </dict>
        </array>
    </dict>
</plist>
